LICENSE
MANIFEST.in
README.rst
setup.py
continuous_scripts/__init__.py
continuous_scripts.egg-info/PKG-INFO
continuous_scripts.egg-info/SOURCES.txt
continuous_scripts.egg-info/dependency_links.txt
continuous_scripts.egg-info/top_level.txt
continuous_scripts/scripts/bootstrap.sh
continuous_scripts/scripts/logmonitor.sh
continuous_scripts/scripts/continuousrc/python
continuous_scripts/scripts/continuousrc/ruby
continuous_scripts/scripts/continuousrc/skeleton
continuous_scripts/scripts/services/memcached
continuous_scripts/scripts/services/mongodb
continuous_scripts/scripts/services/mysql
continuous_scripts/scripts/services/postgresql8.4
continuous_scripts/scripts/services/postgresql9
continuous_scripts/scripts/services/redis
continuous_scripts/scripts/setupscripts/python
continuous_scripts/scripts/setupscripts/ruby
continuous_scripts/scripts/setupscripts/skeleton