Metadata-Version: 1.0
Name: continuous-scripts
Version: 0.1
Summary: Scripts for use by continuous.io
Home-page: https://github.com/continuous/scripts
Author: Adam Charnock
Author-email: adam@continuous.io
License: Apache Software License
Platform: UNKNOWN
Classifier: Intended Audience :: Developers
Classifier: Natural Language :: English
